jaseci_kit/__init__.py
jaseci_kit/bi_enc.py
jaseci_kit/cl_summer.py
jaseci_kit/ent_ext.py
jaseci_kit/fast_enc.py
jaseci_kit/pdf_ext.py
jaseci_kit/t5_sum.py
jaseci_kit/text_seg.py
jaseci_kit/tfm_ner.py
jaseci_kit/use_enc.py
jaseci_kit/use_qa.py
jaseci_kit/modules/__init__.py
jaseci_kit/modules/cl_summer/__init__.py
jaseci_kit/modules/cl_summer/cl_summer.py
jaseci_kit/modules/cl_summer/tests/__init__.py
jaseci_kit/modules/cl_summer/tests/test_cl_summary.py
jaseci_kit/modules/cl_summer/tests/test_data.py
jaseci_kit/modules/encoders/__init__.py
jaseci_kit/modules/encoders/bi_enc.py
jaseci_kit/modules/encoders/poly_enc.py
jaseci_kit/modules/encoders/sent_enc.py
jaseci_kit/modules/encoders/tests/__init__.py
jaseci_kit/modules/encoders/tests/test_biencoder.py
jaseci_kit/modules/encoders/tests/test_data.py
jaseci_kit/modules/encoders/utils/__init__.py
jaseci_kit/modules/encoders/utils/evaluate.py
jaseci_kit/modules/encoders/utils/model_config.json
jaseci_kit/modules/encoders/utils/models.py
jaseci_kit/modules/encoders/utils/tokenizer.py
jaseci_kit/modules/encoders/utils/train.py
jaseci_kit/modules/encoders/utils/train_config.json
jaseci_kit/modules/ent_ext/__init__.py
jaseci_kit/modules/ent_ext/config.cfg
jaseci_kit/modules/ent_ext/ent_ext.py
jaseci_kit/modules/ent_ext/entity_utils.py
jaseci_kit/modules/ent_ext/tests/__init__.py
jaseci_kit/modules/ent_ext/tests/test_data.py
jaseci_kit/modules/ent_ext/tests/test_entity.py
jaseci_kit/modules/fast_enc/__init__.py
jaseci_kit/modules/fast_enc/config.py
jaseci_kit/modules/fast_enc/example_training_data.json
jaseci_kit/modules/fast_enc/fast_enc.py
jaseci_kit/modules/fast_enc/json_to_train.py
jaseci_kit/modules/fast_enc/tests/__init__.py
jaseci_kit/modules/fast_enc/tests/test_data.py
jaseci_kit/modules/fast_enc/tests/test_fast_enc.py
jaseci_kit/modules/pdf_ext/__init__.py
jaseci_kit/modules/pdf_ext/pdf_ext.py
jaseci_kit/modules/pdf_ext/tests/__init__.py
jaseci_kit/modules/pdf_ext/tests/test_data.py
jaseci_kit-1.3.4.8.dist-info/METADATA
jaseci_kit-1.3.4.8.dist-info/WHEEL
jaseci_kit-1.3.4.8.dist-info/top_level.txt
jaseci_kit-1.3.4.8.dist-info/RECORD
