Metadata-Version: 2.1
Name: jaseci-kit
Version: 1.3.4.8
Requires-Dist: jaseci
Requires-Dist: tensorflow (<3.0.0,>=2.8.0)
Requires-Dist: tensorflow-hub (<1.0.0,>=0.12.0)
Requires-Dist: tensorflow-text (<3.0.0,>=2.7.3)
Requires-Dist: transformers (==4.16.2)
Requires-Dist: torch (<2.0.0,>=1.10.2)
Requires-Dist: pandas (<2.0.0,>=1.4.1)
Requires-Dist: flair (==0.10)
Requires-Dist: numpy (<2.0.0,>=1.22.1)
Requires-Dist: fasttext (<0.10.0,>=0.9.2)
Requires-Dist: spacy (==3.3.0)
Requires-Dist: sumy (<0.10.0,>=0.9.0)
Requires-Dist: PyPDF2 (<1.28,>=1.27.12)
Requires-Dist: evaluate (<0.3,>=0.2.2)
Requires-Dist: seqeval (<1.3,>=1.2.2)
